AIparse/__init__.py
AIparse/parse.py
ai_html_parse-0.1.0.dist-info/METADATA
ai_html_parse-0.1.0.dist-info/WHEEL
ai_html_parse-0.1.0.dist-info/top_level.txt
ai_html_parse-0.1.0.dist-info/RECORD
