Metadata-Version: 2.1
Name: ai-html-parse
Version: 0.1.0
Summary: AI HTML Parser
Home-page: https://github.com/Python-shik/ai-html-parse
Author: Illya Lazarev
Author-email: sbdt.israel@gmail.com
Classifier: Programming Language :: Python :: 3
Classifier: License :: OSI Approved :: MIT License
Classifier: Operating System :: OS Independent
Requires-Python: >=3.10
Requires-Dist: requests
Requires-Dist: bs4
